{"cookies": [{"name": "__cf_bm", "value": "bH.fo0UkDmkZtRXXg70bRgwcnFlKaK_k6xE1YEpNlRo-1767853412-1.0.1.1-olDjTs.qyECjbAdcwWBjFdBPfhm92LHioXf7hrv4N6fu1Ia6Vkzorr.EvkNITYmlc7ZEjx5dsqzeavMaRwji_8gPcQzYIU12MvFkZIe4zwI", "domain": ".store.epicgames.com", "path": "/", "expires": 1767855212.386104, "httpOnly": true, "secure": true, "sameSite": "None"}, {"name": "_epicSID", "value": "cd73253507244858ba8b459225742a50", "domain": ".epicgames.com", "path": "/", "expires": -1, "httpOnly": false, "secure": true, "sameSite": "None"}, {"name": "cf_clearance", "value": "Hc2yLiZ2qPy1BiLHGI.Op6RF.cYK4phXDUD1q.EapPA-1767853414-1.2.1.1-vsaKrRuT_cJhF4_YRvJ1zWo0AgtDSknF22onwsTgbE5Xm.DApUjyfKB_8Jv4pXG4XuEX8LQ9ig8rhr_7kDOXxEC_DrErBN4GQwtNSkR7dbOH_bpBWoX6RhavCUVA8nVpGdJQESAF0B4XVvXzbhpmcCctYMNXbljN3RaATWHYoJU.6IJixifMuigcUz51U2TdR8OU5Xsmi_96fuRhKfKWdurMyWlnn8mapBX9tpVHK4A", "domain": ".store.epicgames.com", "path": "/", "expires": 1799389414.493454, "httpOnly": true, "secure": true, "sameSite": "None", "partitionKey": "https://epicgames.com", "_crHasCrossSiteAncestor": false}, {"name": "__cf_bm", "value": "5nwYm1lU8SCK0zY450..jRKEB8ZPzvgYaBUiE13Fiig-1767853414-1.0.1.1-aUlFGsyfo0Dh69Y_onVDUMwD_Q7CjY6Q246EBmGZo6HgiyowHlncTDJ2F0UN6U0CD5.Owkv8bIFA7nWjJr5ptZ950Jie0nlfnQSgrmwoazY", "domain": ".static-assets-prod.epicgames.com", "path": "/", "expires": 1767855214.80177, "httpOnly": true, "secure": true, "sameSite": "None"}], "origins": [{"origin": "https://store.epicgames.com", "localStorage": [{"name": "epicVideoSettings", "value": "{\"autoplay\":true}"}, {"name": "dashjs_audio_settings", "value": "{\"settings\":{\"lang\":\"\",\"viewpoint\":[],\"audioChannelConfiguration\":{\"schemeIdUri\":\"urn:mpeg:dash:23003:3:audio_channel_configuration:2011\",\"value\":\"2\",\"id\":null},\"codec\":\"audio/mp4;codecs=\\\"mp4a.40.2\\\"\"},\"timestamp\":1767853200000}"}, {"name": "dashjs_video_bitrate", "value": "{\"bitrate\":\"212279.000\",\"timestamp\":1767853200000}"}, {"name": "dashjs_video_settings", "value": "{\"settings\":{\"lang\":\"\",\"viewpoint\":[],\"codec\":\"video/mp4;codecs=\\\"avc1.64001f\\\"\"},\"timestamp\":1767853200000}"}]}]}